holmc/__init__.py
holmc/samplers/__init__.py
holmc/samplers/base.py
holmc/samplers/o3sampler.py
holmc/samplers/o4sampler.py
holmc/utils/__init__.py
holmc/utils/gridsearch.py
holmc/utils/maths.py
holmc/utils/mean.py
holmc/utils/metric.py
holmc/utils/params.py
holmc-0.1.dist-info/licenses/LICENSE
holmc-0.1.dist-info/METADATA
holmc-0.1.dist-info/WHEEL
holmc-0.1.dist-info/top_level.txt
holmc-0.1.dist-info/RECORD
