Metadata-Version: 2.4
Name: holmc
Version: 0.1
Summary: Higher Order Langevin Monte Carlo- A MCMC sampler         for Bayesian inference
Author: Rafiq Islam
Author-email: rislam@fsu.edu
License: MIT
License-File: LICENSE
Requires-Dist: numpy
Requires-Dist: matplotlib
Requires-Dist: seaborn
Requires-Dist: tqdm
Requires-Dist: scipy
Requires-Dist: pandas
Requires-Dist: sympy
Requires-Dist: scikit-learn
Requires-Dist: ucimlrepo
Provides-Extra: dev
Requires-Dist: black; extra == "dev"
Requires-Dist: isort; extra == "dev"
Requires-Dist: pre-commit; extra == "dev"
Dynamic: author
Dynamic: author-email
Dynamic: license
Dynamic: license-file
Dynamic: provides-extra
Dynamic: requires-dist
Dynamic: summary
